evaluate_service/__init__.py
evaluate_service/class_factory.py
evaluate_service/main.py
evaluate_service/run_flask.py
evaluate_service/hardwares/__init__.py
evaluate_service/hardwares/davinci/compile_atlas300.sh
evaluate_service/hardwares/davinci/davinci.py
evaluate_service/hardwares/davinci/get_latency_from_log.sh
evaluate_service/hardwares/davinci/inference_atlas300.sh
evaluate_service/hardwares/davinci/model_convert.sh
evaluate_service/hardwares/davinci/samples/atlas300/inc/model_process.h
evaluate_service/hardwares/davinci/samples/atlas300/inc/sample_process.h
evaluate_service/hardwares/davinci/samples/atlas300/inc/utils.h
evaluate_service/hardwares/davinci/samples/atlas300/src/CMakeLists.txt
evaluate_service/hardwares/davinci/samples/atlas300/src/acl.json
evaluate_service/hardwares/davinci/samples/atlas300/src/main.cpp
evaluate_service/hardwares/davinci/samples/atlas300/src/model_process.cpp
evaluate_service/hardwares/davinci/samples/atlas300/src/sample_process.cpp
evaluate_service/hardwares/davinci/samples/atlas300/src/utils.cpp
evaluate_service/security/__init__.py
evaluate_service/security/args.py
evaluate_service/security/check_env.py
evaluate_service/security/conf.py
evaluate_service/security/load_pickle.py
evaluate_service/security/post.py
evaluate_service/security/run_dask.py
evaluate_service/security/utils.py
evaluate_service/security/verify_cert.py
evaluate_service/security/verify_config.py
evaluate_service/security/zmq_op.py
evaluate_service/security/kmc/encrypt_key.py
evaluate_service/security/kmc/kmc.py
evaluate_service/security/kmc/utils.py
evaluate_service-1.8.5.dist-info/LICENSE
evaluate_service-1.8.5.dist-info/METADATA
evaluate_service-1.8.5.dist-info/WHEEL
evaluate_service-1.8.5.dist-info/entry_points.txt
evaluate_service-1.8.5.dist-info/top_level.txt
evaluate_service-1.8.5.dist-info/RECORD
