Metadata-Version: 2.1
Name: evaluate-service
Version: 1.8.5
Summary: AutoML Toolkit
Home-page: https://github.com/huawei-noah/vega/evaluate-service
Author: Huawei Noah's Ark Lab
Author-email: 
License: Apache License 2.0
Platform: UNKNOWN
Classifier: Programming Language :: Python :: 3
Classifier: License :: OSI Approved :: Apache Software License
Classifier: Operating System :: POSIX :: Linux
Requires-Python: >=3.6
Requires-Dist: Flask-RESTful
Requires-Dist: Flask-Limiter
Requires-Dist: gevent
Requires-Dist: PyYAML
